experta/__init__.py
experta/abstract.py
experta/activation.py
experta/agenda.py
experta/conditionalelement.py
experta/deffacts.py
experta/engine.py
experta/fact.py
experta/factlist.py
experta/fieldconstraint.py
experta/frozenfact.py
experta/operator.py
experta/pattern.py
experta/rule.py
experta/shortcuts.py
experta/strategies.py
experta/utils.py
experta/watchers.py
experta/matchers/__init__.py
experta/matchers/rete/__init__.py
experta/matchers/rete/abstract.py
experta/matchers/rete/check.py
experta/matchers/rete/dnf.py
experta/matchers/rete/mixins.py
experta/matchers/rete/nodes.py
experta/matchers/rete/token.py
experta/matchers/rete/utils.py
experta-1.9.3.dist-info/LICENSE
experta-1.9.3.dist-info/METADATA
experta-1.9.3.dist-info/WHEEL
experta-1.9.3.dist-info/top_level.txt
experta-1.9.3.dist-info/RECORD
