Metadata-Version: 2.1
Name: experta
Version: 1.9.3
Summary: Expert Systems for Python
Home-page: https://github.com/nilp0inter/experta
Author: UNKNOWN
Author-email: UNKNOWN
License: LGPLv3
Keywords: knowledge-based,inference,engine
Platform: UNKNOWN
Classifier: Programming Language :: Python :: 3.5
Classifier: Programming Language :: Python :: 3.6
Classifier: Programming Language :: Python :: 3.7
Classifier: Programming Language :: Python :: 3.8
Classifier: Programming Language :: Python :: Implementation :: PyPy
Requires-Dist: frozendict (==1.2)
Requires-Dist: schema (==0.6.7)
